vbench2/VBench2_full_info.json
vbench2/__init__.py
vbench2/camera_motion.py
vbench2/complex_landscape.py
vbench2/complex_plot.py
vbench2/composition.py
vbench2/distributed.py
vbench2/diversity.py
vbench2/dynamic_attribute.py
vbench2/dynamic_spatial_relationship.py
vbench2/hack_registry.py
vbench2/human_anatomy.py
vbench2/human_clothes.py
vbench2/human_identity.py
vbench2/human_interaction.py
vbench2/instance_preservation.py
vbench2/material.py
vbench2/mechanics.py
vbench2/motion_order_understanding.py
vbench2/motion_rationality.py
vbench2/multi_view_consistency.py
vbench2/thermotics.py
vbench2/utils.py
vbench2/cli/__init__.py
vbench2/cli/evaluate.py
vbench2/cli/vbench2.py
vbench2/launch/__init__.py
vbench2/launch/evaluate.py
vbench2/third_party/LLaVA_NeXT/cog.yaml
vbench2/third_party/LLaVA_NeXT/requirements.txt
vbench2/third_party/LLaVA_NeXT/llava/model/multimodal_encoder/dev_eva_clip/eva_clip/model_configs/EVA-CLIP-18B.json
vbench2/third_party/LLaVA_NeXT/llava/model/multimodal_encoder/dev_eva_clip/eva_clip/model_configs/EVA-CLIP-8B-plus.json
vbench2/third_party/LLaVA_NeXT/llava/model/multimodal_encoder/dev_eva_clip/eva_clip/model_configs/EVA-CLIP-8B.json
vbench2/third_party/LLaVA_NeXT/llava/model/multimodal_encoder/dev_eva_clip/eva_clip/model_configs/EVA01-CLIP-B-16.json
vbench2/third_party/LLaVA_NeXT/llava/model/multimodal_encoder/dev_eva_clip/eva_clip/model_configs/EVA01-CLIP-g-14-plus.json
vbench2/third_party/LLaVA_NeXT/llava/model/multimodal_encoder/dev_eva_clip/eva_clip/model_configs/EVA01-CLIP-g-14.json
vbench2/third_party/LLaVA_NeXT/llava/model/multimodal_encoder/dev_eva_clip/eva_clip/model_configs/EVA02-CLIP-B-16.json
vbench2/third_party/LLaVA_NeXT/llava/model/multimodal_encoder/dev_eva_clip/eva_clip/model_configs/EVA02-CLIP-L-14-336.json
vbench2/third_party/LLaVA_NeXT/llava/model/multimodal_encoder/dev_eva_clip/eva_clip/model_configs/EVA02-CLIP-L-14.json
vbench2-0.1.1.dist-info/METADATA
vbench2-0.1.1.dist-info/WHEEL
vbench2-0.1.1.dist-info/entry_points.txt
vbench2-0.1.1.dist-info/top_level.txt
vbench2-0.1.1.dist-info/RECORD
