Metadata-Version: 2.2
Name: vbench2
Version: 0.1.1
Summary: Video generation benchmark
License: Apache Software License 2.0
Project-URL: Source, https://github.com/Vchitect/VBench/tree/master/VBench-2.0
Requires-Dist: accelerate==1.2.1
Requires-Dist: addict==2.4.0
Requires-Dist: aiohappyeyeballs==2.4.4
Requires-Dist: aiohttp==3.11.11
Requires-Dist: aiosignal==1.3.2
Requires-Dist: albucore==0.0.19
Requires-Dist: albumentations==1.4.19
Requires-Dist: annotated-types==0.7.0
Requires-Dist: antlr4-python3-runtime==4.9.3
Requires-Dist: anyio==4.8.0
Requires-Dist: args==0.1.0
Requires-Dist: async-timeout==5.0.1
Requires-Dist: attrs==24.3.0
Requires-Dist: av==14.0.1
Requires-Dist: beautifulsoup4==4.12.3
Requires-Dist: bitsandbytes==0.42.0
Requires-Dist: blis==1.2.0
Requires-Dist: boto3==1.26.90
Requires-Dist: botocore
Requires-Dist: braceexpand==0.1.7
Requires-Dist: catalogue==2.0.10
Requires-Dist: certifi==2024.12.14
Requires-Dist: charset-normalizer==3.4.1
Requires-Dist: click==8.1.8
Requires-Dist: clint==0.5.1
Requires-Dist: cloudpickle==3.1.1
Requires-Dist: confection==0.1.5
Requires-Dist: contourpy==1.3.1
Requires-Dist: cycler==0.12.1
Requires-Dist: cymem==2.0.11
Requires-Dist: datasets==3.2.0
Requires-Dist: decorator==5.1.1
Requires-Dist: decord==0.6.0
Requires-Dist: deep-sort-realtime==1.3.2
Requires-Dist: deepspeed==0.12.6
Requires-Dist: defusedxml==0.7.1
Requires-Dist: diffusers==0.32.1
Requires-Dist: dill==0.3.8
Requires-Dist: distro==1.9.0
Requires-Dist: docker-pycreds==0.4.0
Requires-Dist: easydict==1.13
Requires-Dist: einops==0.8.0
Requires-Dist: einops-exts==0.0.4
Requires-Dist: exceptiongroup==1.2.2
Requires-Dist: fairscale==0.4.13
Requires-Dist: fastapi==0.115.6
Requires-Dist: filelock==3.13.1
Requires-Dist: filterpy==1.4.5
Requires-Dist: fire==0.4.0
Requires-Dist: flowlib==0.6.6.8
Requires-Dist: fonttools==4.55.3
Requires-Dist: frozenlist==1.5.0
Requires-Dist: fsspec==2024.2.0
Requires-Dist: ftfy==6.3.1
Requires-Dist: fvcore==0.1.5.post20221221
Requires-Dist: gdown==5.2.0
Requires-Dist: gitdb==4.0.12
Requires-Dist: GitPython==3.1.44
Requires-Dist: h11==0.14.0
Requires-Dist: h5py==3.12.1
Requires-Dist: hjson==3.1.0
Requires-Dist: hpsv2==1.2.0
Requires-Dist: httpcore==1.0.7
Requires-Dist: httpx==0.28.1
Requires-Dist: huggingface-hub==0.27.1
Requires-Dist: idna==3.10
Requires-Dist: imageio==2.37.0
Requires-Dist: imageio-ffmpeg==0.6.0
Requires-Dist: importlib_metadata==8.5.0
Requires-Dist: iniconfig==2.0.0
Requires-Dist: iopath==0.1.10
Requires-Dist: ipdb==0.13.13
Requires-Dist: ipython==8.32.0
Requires-Dist: Jinja2==3.1.3
Requires-Dist: jiter==0.8.2
Requires-Dist: jmespath==1.0.1
Requires-Dist: joblib==1.4.2
Requires-Dist: kiwisolver==1.4.8
Requires-Dist: kornia==0.5.6
Requires-Dist: kornia_rs==0.1.8
Requires-Dist: langcodes==3.5.0
Requires-Dist: lazy_loader==0.4
Requires-Dist: logger==1.4
Requires-Dist: lvis==0.5.3
Requires-Dist: MarkupSafe==2.1.5
Requires-Dist: matplotlib==3.10.0
Requires-Dist: mmdet==3.0.0
Requires-Dist: mmengine==0.10.5
Requires-Dist: mmyolo==0.6.0
Requires-Dist: mpmath==1.3.0
Requires-Dist: msgpack==1.1.0
Requires-Dist: multidict==6.1.0
Requires-Dist: multiprocess==0.70.16
Requires-Dist: murmurhash==1.0.12
Requires-Dist: networkx==3.2.1
Requires-Dist: nltk==3.9.1
Requires-Dist: numpy==1.26.3
Requires-Dist: omegaconf==2.3.0
Requires-Dist: onnx==1.17.0
Requires-Dist: onnxruntime==1.16.3
Requires-Dist: open_clip_torch==2.30.0
Requires-Dist: openai==1.59.5
Requires-Dist: opencv-python==4.10.0.84
Requires-Dist: opencv-python-headless==4.10.0.84
Requires-Dist: openmim==0.3.9
Requires-Dist: packaging==24.2
Requires-Dist: pandas==2.2.3
Requires-Dist: peft==0.14.0
Requires-Dist: pillow==10.2.0
Requires-Dist: platformdirs==4.3.6
Requires-Dist: pluggy==1.5.0
Requires-Dist: portalocker==3.1.1
Requires-Dist: preshed==3.0.9
Requires-Dist: prettytable==3.14.0
Requires-Dist: propcache==0.2.1
Requires-Dist: protobuf==3.20.3
Requires-Dist: py-cpuinfo==9.0.0
Requires-Dist: pyarrow==18.1.0
Requires-Dist: pycocoevalcap==1.2
Requires-Dist: pycocotools==2.0.8
Requires-Dist: pydantic==2.10.4
Requires-Dist: pydantic_core==2.27.2
Requires-Dist: pyecharts==2.0.8
Requires-Dist: pynvml==12.0.0
Requires-Dist: pyparsing==3.2.1
Requires-Dist: PySocks==1.7.1
Requires-Dist: pytest==7.2.0
Requires-Dist: pytest-split==0.8.0
Requires-Dist: python-dateutil==2.9.0.post0
Requires-Dist: pytz==2024.2
Requires-Dist: PyYAML==6.0.2
Requires-Dist: qudida==0.0.4
Requires-Dist: regex==2024.11.6
Requires-Dist: requests==2.32.3
Requires-Dist: rich==13.9.4
Requires-Dist: safetensors==0.5.2
Requires-Dist: scenedetect==0.6.5.2
Requires-Dist: scikit-image==0.25.0
Requires-Dist: scikit-learn==1.6.0
Requires-Dist: scipy==1.15.0
Requires-Dist: seaborn==0.13.2
Requires-Dist: selenium==4.29.0
Requires-Dist: sentencepiece==0.2.0
Requires-Dist: sentry-sdk==2.19.2
Requires-Dist: setproctitle==1.3.4
Requires-Dist: shapely==2.0.7
Requires-Dist: simplejson==3.20.1
Requires-Dist: six==1.17.0
Requires-Dist: smmap==5.0.2
Requires-Dist: snapshot-selenium==0.0.2
Requires-Dist: sniffio==1.3.1
Requires-Dist: soupsieve==2.6
Requires-Dist: spacy==3.8.4
Requires-Dist: srsly==2.5.1
Requires-Dist: stack-data==0.6.3
Requires-Dist: starlette==0.41.3
Requires-Dist: sympy==1.13.1
Requires-Dist: tabulate==0.9.0
Requires-Dist: termcolor==2.5.0
Requires-Dist: terminaltables==3.1.10
Requires-Dist: thinc
Requires-Dist: thop==0.1.1.post2209072238
Requires-Dist: threadpoolctl==3.5.0
Requires-Dist: tifffile==2025.1.10
Requires-Dist: tiktoken==0.8.0
Requires-Dist: timesformer-pytorch==0.4.1
Requires-Dist: timm==0.4.12
Requires-Dist: tokenizers==0.21.1
Requires-Dist: tomli==2.2.1
Requires-Dist: tqdm==4.67.1
Requires-Dist: traitlets==5.14.3
Requires-Dist: transformers==4.47.1
Requires-Dist: triton==3.1.0
Requires-Dist: typing_extensions==4.12.2
Requires-Dist: tzdata==2024.2
Requires-Dist: ultralytics==8.3.68
Requires-Dist: unicorn==2.1.1
Requires-Dist: urllib3==1.26.15
Requires-Dist: wandb==0.19.2
Requires-Dist: wasabi==1.1.3
Requires-Dist: wcwidth==0.2.13
Requires-Dist: webdataset==0.2.100
Requires-Dist: websocket==0.2.1
Requires-Dist: websocket-client==1.8.0
Requires-Dist: wordcloud==1.9.4
Requires-Dist: xxhash==3.5.0
Requires-Dist: yacs==0.1.8
Requires-Dist: yapf==0.43.0
Requires-Dist: yarl==1.18.3
Requires-Dist: yolov5
Requires-Dist: zipp==3.21.0
Requires-Dist: mediapipe
Requires-Dist: retina-face
Requires-Dist: retinaface-pytorch
Requires-Dist: supervision
Dynamic: description
Dynamic: description-content-type
Dynamic: license
Dynamic: project-url
Dynamic: requires-dist
Dynamic: summary
